<annotation>
	<folder>train</folder>
	<filename>IMG_20181004_171341.jpg</filename>
	<path>C:\Users\juanp\Documents\JPB\Universidad\Proyecto de grado\Vision por computador\Base de datos\stairs_dataset\train\IMG_20181004_171341.jpg</path>
	<source>
		<database>Unknown</database>
	</source>
	<size>
		<width>1632</width>
		<height>918</height>
		<depth>3</depth>
	</size>
	<segmented>0</segmented>
	<object>
		<name>stairs_up</name>
		<pose>Unspecified</pose>
		<truncated>0</truncated>
		<difficult>0</difficult>
		<bndbox>
			<xmin>23</xmin>
			<ymin>14</ymin>
			<xmax>1375</xmax>
			<ymax>659</ymax>
		</bndbox>
	</object>
</annotation>
