<annotation>
	<folder>Stairs</folder>
	<filename>STR_S1_37.jpg</filename>
	<path>C:\Users\juanp\Documents\JPB\Universidad\Proyecto de grado\Vision por computador\Base de datos\MCIndoor dataset\Stairs\STR_S1_37.jpg</path>
	<source>
		<database>Unknown</database>
	</source>
	<size>
		<width>3120</width>
		<height>4160</height>
		<depth>3</depth>
	</size>
	<segmented>0</segmented>
	<object>
		<name>stairs_up</name>
		<pose>Unspecified</pose>
		<truncated>0</truncated>
		<difficult>0</difficult>
		<bndbox>
			<xmin>83</xmin>
			<ymin>864</ymin>
			<xmax>2924</xmax>
			<ymax>3823</ymax>
		</bndbox>
	</object>
</annotation>
